[
  {
    "Id": "00f5c33a-8ca4-4fa0-a11b-ce616f1e982b",
    "Name": "VRIGNAUD",
    "Firstname": "Isabelle",
    "Status": "Accepté",
    "RelatedTo": "Léa",
    "Relation": "Famille"
  },
  {
    "Id": "00f5c33a-8ca4-4fa0-a11b-ce616f1e982b",
    "Name": "FRANCHETEAU",
    "Firstname": "Pascal",
    "Status": "Accepté",
    "RelatedTo": "Léa",
    "Relation": "Famille"
  },
  {
    "Id": "00f5c33a-8ca4-4fa0-a11b-ce616f1e982b",
    "Name": "FRANCHETEAU",
    "Firstname": "Angèle",
    "Status": "Accepté",
    "RelatedTo": "Léa",
    "Relation": "Famille"
  },
  {
    "Id": "00f5c33a-8ca4-4fa0-a11b-ce616f1e982b",
    "Name": "FRANCHETEAU",
    "Firstname": "Alexis",
    "Status": "Accepté",
    "RelatedTo": "Léa",
    "Relation": "Famille"
  },
  {
    "Id": "00f5c33a-8ca4-4fa0-a11b-ce616f1e982b",
    "Name": "FRANCHETEAU",
    "Firstname": "Thierry",
    "Status": "En attente",
    "RelatedTo": "Léa",
    "Relation": "Famille"
  },
  {
    "Id": "00f5c33a-8ca4-4fa0-a11b-ce616f1e982b",
    "Name": "FRANCHETEAU",
    "Firstname": "Joël",
    "Status": "Accepté",
    "RelatedTo": "Léa",
    "Relation": "Famille"
  },

  {
    "Id": "00f5c33a-8ca4-4fa0-a11b-ce616f1e982b",
    "Name": "FRANCHETEAU",
    "Firstname": "Annie",
    "Status": "Accepté",
    "RelatedTo": "Léa",
    "Relation": "Famille"
  },
  {
    "Id": "00f5c33a-8ca4-4fa0-a11b-ce616f1e982b",
    "Name": "Mathias",
    "Firstname": "Alexis",
    "Status": "En attente",
    "RelatedTo": "Léa",
    "Relation": "Famille"
  },

  {
    "Id": "00f5c33a-8ca4-4fa0-a11b-ce616f1e982b",
    "Name": "FRANCHETEAU",
    "Firstname": "Dorian",
    "Status": "En attente",
    "RelatedTo": "Léa",
    "Relation": "Famille"
  },
  {
    "Id": "00f5c33a-8ca4-4fa0-a11b-ce616f1e982b",
    "Name": "FRANCHETEAU",
    "Firstname": "Cyril",
    "Status": "En attente",
    "RelatedTo": "Léa",
    "Relation": "Famille"
  },
  {
    "Id": "00f5c33a-8ca4-4fa0-a11b-ce616f1e982b",
    "Name": "SABOURAUD",
    "Firstname": "Emeline",
    "Status": "En attente",
    "RelatedTo": "Léa",
    "Relation": "Famille"
  },
  {
    "Id": "00f5c33a-8ca4-4fa0-a11b-ce616f1e982b",
    "Name": "VRIGNAUD",
    "Firstname": "Alain",
    "Status": "En attente",
    "RelatedTo": "Léa",
    "Relation": "Famille"
  },
  {
    "Id": "00f5c33a-8ca4-4fa0-a11b-ce616f1e982b",
    "Name": "VRIGNAUD",
    "Firstname": "Anne",
    "Status": "En attente",
    "RelatedTo": "Léa",
    "Relation": "Famille"
  },
  {
    "Id": "00f5c33a-8ca4-4fa0-a11b-ce616f1e982b",
    "Name": "VRIGNAUD",
    "Firstname": "Tom",
    "Status": "En attente",
    "RelatedTo": "Léa",
    "Relation": "Famille"
  },
  {
    "Id": "00f5c33a-8ca4-4fa0-a11b-ce616f1e982b",
    "Name": "ROMEFORT",
    "Firstname": "Louise",
    "Status": "En attente",
    "RelatedTo": "Léa",
    "Relation": "Famille"
  },
  {
    "Id": "00f5c33a-8ca4-4fa0-a11b-ce616f1e982b",
    "Name": "VRIGNAUD",
    "Firstname": "Zoé",
    "Status": "En attente",
    "RelatedTo": "Léa",
    "Relation": "Famille"
  },
  {
    "Id": "00f5c33a-8ca4-4fa0-a11b-ce616f1e982b",
    "Name": "VRIGNAUD",
    "Firstname": "Bob",
    "Status": "En attente",
    "RelatedTo": "Léa",
    "Relation": "Famille"
  },
  {
    "Id": "00f5c33a-8ca4-4fa0-a11b-ce616f1e982b",
    "Name": "VRIGNAUD",
    "Firstname": "Philippe",
    "Status": "En attente",
    "RelatedTo": "Léa",
    "Relation": "Famille"
  },
  {
    "Id": "00f5c33a-8ca4-4fa0-a11b-ce616f1e982b",
    "Name": "VRIGNAUD",
    "Firstname": "Pascal",
    "Status": "En attente",
    "RelatedTo": "Léa",
    "Relation": "Famille"
  },
  {
    "Id": "00f5c33a-8ca4-4fa0-a11b-ce616f1e982b",
    "Name": "VRIGNAUD",
    "Firstname": "Hugo",
    "Status": "En attente",
    "RelatedTo": "Léa",
    "Relation": "Famille"
  },
  {
    "Id": "00f5c33a-8ca4-4fa0-a11b-ce616f1e982b",
    "Name": "UNKNOWN",
    "Firstname": "Mél",
    "Status": "En attente",
    "RelatedTo": "Léa",
    "Relation": "Famille"
  },
  {
    "Id": "00f5c33a-8ca4-4fa0-a11b-ce616f1e982b",
    "Name": "VRIGNAUD",
    "Firstname": "Emma",
    "Status": "En attente",
    "RelatedTo": "Léa",
    "Relation": "Famille"
  },
  {
    "Id": "00f5c33a-8ca4-4fa0-a11b-ce616f1e982b",
    "Name": "ZINS",
    "Firstname": "Catherine",
    "Status": "En attente",
    "RelatedTo": "Léa",
    "Relation": "Famille"
  },
  {
    "Id": "00f5c33a-8ca4-4fa0-a11b-ce616f1e982b",
    "Name": "ZINS",
    "Firstname": "Frédéric",
    "Status": "En attente",
    "RelatedTo": "Léa",
    "Relation": "Famille"
  },
  {
    "Id": "00f5c33a-8ca4-4fa0-a11b-ce616f1e982b",
    "Name": "ZINS",
    "Firstname": "Gabriel",
    "Status": "En attente",
    "RelatedTo": "Léa",
    "Relation": "Famille"
  },
  {
    "Id": "00f5c33a-8ca4-4fa0-a11b-ce616f1e982b",
    "Name": "ZINS",
    "Firstname": "Achille",
    "Status": "En attente",
    "RelatedTo": "Léa",
    "Relation": "Famille"
  },
  {
    "Id": "00f5c33a-8ca4-4fa0-a11b-ce616f1e982b",
    "Name": "VRIGNAUD",
    "Firstname": "Bernard",
    "Status": "En attente",
    "RelatedTo": "Léa",
    "Relation": "Famille"
  },
  {
    "Id": "00f5c33a-8ca4-4fa0-a11b-ce616f1e982b",
    "Name": "PINCEMAILLE",
    "Firstname": "Charles",
    "Status": "En attente",
    "RelatedTo": "Alexandre",
    "Relation": "Ami"
  },
  {
    "Id": "00f5c33a-8ca4-4fa0-a11b-ce616f1e982b",
    "Name": "DOE",
    "Firstname": "John",
    "Status": "Refusé",
    "RelatedTo": "Alexandre",
    "Relation": "Ami"
  }
] 